logux/__init__.py
logux/logux.py
logux-0.0.5.dist-info/AUTHORS.md
logux-0.0.5.dist-info/LICENSE
logux-0.0.5.dist-info/METADATA
logux-0.0.5.dist-info/WHEEL
logux-0.0.5.dist-info/top_level.txt
logux-0.0.5.dist-info/RECORD
