Metadata-Version: 2.1
Name: logux
Version: 0.0.5
Summary: The Python interface to the Logux server.
Home-page: https://github.com/nazarov-tech/logux-py
Author: Dmitry Nazarov
Author-email: mail@nazarov.tech
License: MIT license
Keywords: logux
Platform: UNKNOWN
Classifier: Development Status :: 2 - Pre-Alpha
Classifier: Intended Audience :: Developers
Classifier: License :: OSI Approved :: MIT License
Classifier: Natural Language :: English
Classifier: Programming Language :: Python :: 3.5
Classifier: Programming Language :: Python :: 3.6
Classifier: Programming Language :: Python :: 3.7
